sc2gameLobby/__init__.py
sc2gameLobby/__main__.py
sc2gameLobby/__version__.py
sc2gameLobby/cli.py
sc2gameLobby/clientManagement.py
sc2gameLobby/connectToServer.py
sc2gameLobby/dateFormat.py
sc2gameLobby/debugCmds.py
sc2gameLobby/gameConfig.py
sc2gameLobby/gameConstants.py
sc2gameLobby/genericObservation.py
sc2gameLobby/getGameData.py
sc2gameLobby/hostGame.py
sc2gameLobby/ipAddresses.py
sc2gameLobby/joinGame.py
sc2gameLobby/launcher.py
sc2gameLobby/resultHandler.py
sc2gameLobby/setScenario.py
sc2gameLobby/uiControl.py
sc2gameLobby/versions.py
sc2gameLobby/activeGames/__init__.py
sc2gameLobby/jsonData/versions.json
sc2gameLobby/mods/Playground (1).SC2Mod
sc2gameLobby/mods/Playground - Copy.SC2Mod
sc2gameLobby/mods/Playground -- working.SC2Mod
sc2gameLobby/mods/Base67188/Playground - Copy.SC2Mod
sc2gameLobby/mods/Base67188/Playground - old.SC2Mod
sc2gameLobby/mods/Base67188/Playground old.SC2Mod
sc2gameLobby/mods/Base67188/Playground.SC2Mod
sc2gameLobby/runConfigs/__init__.py
sc2gameLobby/runConfigs/platforms.py
sc2gameLobby-1.1.13.dist-info/METADATA
sc2gameLobby-1.1.13.dist-info/RECORD
sc2gameLobby-1.1.13.dist-info/WHEEL
sc2gameLobby-1.1.13.dist-info/entry_points.txt
sc2gameLobby-1.1.13.dist-info/top_level.txt
