Metadata-Version: 2.1
Name: sc2gameLobby
Version: 1.1.13
Summary: An interface to request SC2 matches and launch the client for human and/or AI/bot play
Home-page: https://github.com/ttinies/sc2gameLobby
Author: ttinies
Author-email: help.fool@versentiedge.com
License: Apache License 2.0
Platform: UNKNOWN
Classifier: License :: OSI Approved :: Apache Software License
Classifier: Programming Language :: Python
Classifier: Programming Language :: Python :: 3
Classifier: Programming Language :: Python :: 3.6
Classifier: Programming Language :: Python :: Implementation :: CPython
Classifier: Programming Language :: Python :: Implementation :: PyPy
Classifier: Topic :: Games/Entertainment :: Real Time Strategy
Classifier: Topic :: Scientific/Engineering :: Artificial Intelligence
Requires-Python: >3.4
Requires-Dist: six
Requires-Dist: pySC2
Requires-Dist: s2clientprotocol
Requires-Dist: portpicker
Requires-Dist: sc2common
Requires-Dist: sc2ladderMgmt
Requires-Dist: sc2maptool
Requires-Dist: sc2players
